MANIFEST.in
README.rst
setup.cfg
setup.py
postman_problems/__init__.py
postman_problems/graph.py
postman_problems/postman_chinese.py
postman_problems/postman_rural.py
postman_problems/postman_template.py
postman_problems/solver.py
postman_problems/stats.py
postman_problems/viz.py
postman_problems.egg-info/PKG-INFO
postman_problems.egg-info/SOURCES.txt
postman_problems.egg-info/dependency_links.txt
postman_problems.egg-info/entry_points.txt
postman_problems.egg-info/requires.txt
postman_problems.egg-info/top_level.txt
postman_problems/examples/__init__.py
postman_problems/examples/seven_bridges/__init__.py
postman_problems/examples/seven_bridges/cpp_seven_bridges.py
postman_problems/examples/seven_bridges/edgelist_seven_bridges.csv
postman_problems/examples/sleeping_giant/__init__.py
postman_problems/examples/sleeping_giant/cpp_sleeping_giant.py
postman_problems/examples/sleeping_giant/edgelist_sleeping_giant.csv
postman_problems/examples/sleeping_giant/nodelist_sleeping_giant.csv
postman_problems/examples/sleeping_giant/rpp_sleeping_giant.py
postman_problems/examples/star/__init__.py
postman_problems/examples/star/rpp_star.py
postman_problems/tests/__init__.py
postman_problems/tests/test_chinese_postman.py
postman_problems/tests/test_example_sleeping_giant.py
postman_problems/tests/test_graph.py
postman_problems/tests/test_rural_postman.py
postman_problems/tests/test_solver.py
postman_problems/tests/test_stats.py
postman_problems/tests/test_viz.py
postman_problems/tests/utils.py