Metadata-Version: 2.1
Name: postman-problems
Version: 0.3
Summary: Solutions to Postman graph optimization problems: Chinese and Rural Postman problems
Home-page: https://github.com/brooksandrew/postman_problems
Author: Andrew Brooks
Author-email: andrewbrooks@gmail.com
License: MIT License
Download-URL: https://github.com/brooksandrew/postman_problems/archive/v0.3.tar.gz
Keywords: chinese postman problem networkx optimization network graph arc routing
Platform: UNKNOWN
Classifier: Development Status :: 2 - Pre-Alpha
Classifier: Topic :: Scientific/Engineering :: Mathematics
Classifier: Topic :: Scientific/Engineering :: Visualization
Classifier: License :: OSI Approved :: MIT License
Requires-Python: >=2.7
Provides-Extra: test
Provides-Extra: viz
